[
  [
    {
      "x": 4,
      "a": 7
    },
    ""
  ],
  [
    {
      "y": -0.875,
      "x": 3
    },
    "",
    {
      "x": 1
    },
    ""
  ],
  [
    {
      "y": -0.875,
      "x": 6
    },
    "",
    ""
  ],
  [
    {
      "y": -0.875,
      "x": 1
    },
    "",
    ""
  ],
  [
    {
      "y": -0.375,
      "x": 4
    },
    ""
  ],
  [
    {
      "y": -0.875,
      "x": 3
    },
    "",
    {
      "x": 1
    },
    ""
  ],
  [
    {
      "y": -0.875,
      "x": 6
    },
    "",
    {
      "h": 1.5
    },
    ""
  ],
  [
    {
      "y": -0.875,
      "x": 0.5,
      "w": 1.5
    },
    "",
    ""
  ],
  [
    {
      "y": -0.375,
      "x": 4
    },
    ""
  ],
  [
    {
      "y": -0.875,
      "x": 3
    },
    "",
    {
      "x": 1,
      "n": true
    },
    ""
  ],
  [
    {
      "y": -0.875,
      "x": 6
    },
    ""
  ],
  [
    {
      "y": -0.875,
      "x": 0.25,
      "w": 1.75
    },
    "",
    ""
  ],
  [
    {
      "y": -0.625,
      "x": 7,
      "h": 1.5
    },
    ""
  ],
  [
    {
      "y": -0.75,
      "x": 4
    },
    ""
  ],
  [
    {
      "y": -0.875,
      "x": 3
    },
    "",
    {
      "x": 1
    },
    ""
  ],
  [
    {
      "y": -0.875,
      "x": 6
    },
    ""
  ],
  [
    {
      "y": -0.875,
      "x": 0.25,
      "w": 1.75
    },
    "",
    ""
  ],
  [
    {
      "y": -0.375,
      "x": 4
    },
    ""
  ],
  [
    {
      "y": -0.875,
      "x": 3
    },
    ""
  ],
  [
    {
      "y": -0.75,
      "x": 0.75,
      "w": 1.25
    },
    "",
    ""
  ],
  [
    {
      "r": 15,
      "rx": 7,
      "ry": 4.25,
      "y": 0.34999999999999964,
      "x": -1.6500000000000004,
      "w": 1.25
    },
    ""
  ],
  [
    {
      "r": 30,
      "y": -2.3499999999999996,
      "x": 1
    },
    ""
  ],
  [
    {
      "h": 2
    },
    "",
    {
      "h": 2
    },
    ""
  ]
]